cron/__init__.py
cron/cron.py
tests/__init__.py
tests/test_cron.py
cron_processor-0.1.0.dist-info/METADATA
cron_processor-0.1.0.dist-info/WHEEL
cron_processor-0.1.0.dist-info/top_level.txt
cron_processor-0.1.0.dist-info/RECORD
